sentry_bigquery/__init__.py
sentry_bigquery/client.py
sentry_bigquery/plugin.py
sentry_bigquery-0.2.2.dist-info/LICENSE
sentry_bigquery-0.2.2.dist-info/METADATA
sentry_bigquery-0.2.2.dist-info/WHEEL
sentry_bigquery-0.2.2.dist-info/entry_points.txt
sentry_bigquery-0.2.2.dist-info/top_level.txt
sentry_bigquery-0.2.2.dist-info/RECORD
