Metadata-Version: 2.1
Name: sentry-bigquery
Version: 0.2.2
Summary: Plugin for Sentry which allows data forward to BigQuery
Home-page: https://github.com/SukachVitally/sentry-bigquery
Author: Vitalii Sukach
Author-email: vitalij.sukach@murka.com
License: MIT
Platform: UNKNOWN
Classifier: Programming Language :: Python :: 3
Classifier: License :: OSI Approved :: MIT License
Classifier: Operating System :: OS Independent
Requires-Python: >=3.6
Requires-Dist: google-cloud-bigquery
